regi/__init__.py
regi/regi.py
rigi-1.0.dist-info/LICENCE.txt
rigi-1.0.dist-info/METADATA
rigi-1.0.dist-info/WHEEL
rigi-1.0.dist-info/top_level.txt
rigi-1.0.dist-info/RECORD
